{"title":"Python 3 Terminal Mode","markdown":{"yaml":{"title":"","format":{"html":{"toc":true,"theme":{"light":"cosmo","dark":"darkly"},"code-fold":true}},"jupyter":"python3"},"headingText":"Python 3 Terminal Mode","containsRefs":false,"markdown":"\n\n\nThis part is to present a simple exemple of sample size process by *Monte Carlo* simulation.\n\n\nOpen your terminal and execute the following command line to obtain a simulation sample size result\n\n```\npython3 run_simulation_terminal_job.py -start 200 -end 10 -NumSimu 1000 -epsilonH0 0.7 -epsilonH1 0.8 -H0 0.7 -alpha 0.05 -power 0.8 -method arcsinus\n```\n\nAll simulations results are printed in the terminal and at the end the following table is printed.\n\n+---------+---------+--------+----------+--------+---------------+--------------+-------------+-------------+\n|   alpha |   power |   size | method   |   time |   global_time |   simulation |   mse_alpha |   mse_power |\n|---------+---------+--------+----------+--------+---------------+--------------+-------------+-------------|\n|   0.031 |   0.93  |    197 | arcsinus |   0.08 |         14.38 |         1000 |  0.00102126 | 0.000875848 |\n|   0.043 |   0.944 |    194 | arcsinus |   0.08 |         14.38 |         1000 |  0.00109952 | 0.000800654 |\n|   0.041 |   0.946 |    193 | arcsinus |   0.08 |         14.38 |         1000 |  0.00110124 | 0.000822513 |\n|   0.049 |   0.923 |    190 | arcsinus |   0.08 |         14.38 |         1000 |  0.00110579 | 0.000867812 |\n|   0.05  |   0.936 |    188 | arcsinus |   0.08 |         14.38 |         1000 |  0.00116913 | 0.000843368 |\n|   0.041 |   0.937 |    185 | arcsinus |   0.08 |         14.38 |         1000 |  0.00104164 | 0.000861563 |\n|   0.043 |   0.918 |    179 | arcsinus |   0.08 |         14.38 |         1000 |  0.00110532 | 0.000951974 |\n|   0.045 |   0.927 |    178 | arcsinus |   0.08 |         14.38 |         1000 |  0.00114249 | 0.000893271 |\n|   0.043 |   0.921 |    171 | arcsinus |   0.08 |         14.38 |         1000 |  0.00117478 | 0.000921501 |\n|   0.048 |   0.916 |    170 | arcsinus |   0.08 |         14.38 |         1000 |  0.00113062 | 0.00094519  |\n|   0.045 |   0.915 |    168 | arcsinus |   0.08 |         14.38 |         1000 |  0.00117041 | 0.000929493 |\n|   0.042 |   0.915 |    167 | arcsinus |   0.08 |         14.38 |         1000 |  0.00116929 | 0.000938062 |\n|   0.047 |   0.923 |    166 | arcsinus |   0.08 |         14.38 |         1000 |  0.00121067 | 0.000925817 |\n|   0.05  |   0.94  |    161 | arcsinus |   0.08 |         14.38 |         1000 |  0.00126986 | 0.000935087 |\n|   0.047 |   0.91  |    158 | arcsinus |   0.08 |         14.38 |         1000 |  0.00130337 | 0.000991019 |\n|   0.038 |   0.877 |    153 | arcsinus |   0.08 |         14.38 |         1000 |  0.0014489  | 0.00108544  |\n|   0.047 |   0.917 |    151 | arcsinus |   0.08 |         14.38 |         1000 |  0.00129249 | 0.00104089  |\n|   0.039 |   0.881 |    149 | arcsinus |   0.08 |         14.38 |         1000 |  0.00148851 | 0.00115507  |\n|   0.05  |   0.89  |    148 | arcsinus |   0.08 |         14.38 |         1000 |  0.00140944 | 0.00104022  |\n|   0.042 |   0.849 |    146 | arcsinus |   0.08 |         14.38 |         1000 |  0.00147038 | 0.00119897  |\n|   0.046 |   0.887 |    145 | arcsinus |   0.08 |         14.38 |         1000 |  0.001362   | 0.00104656  |\n|   0.027 |   0.862 |    142 | arcsinus |   0.08 |         14.38 |         1000 |  0.00147959 | 0.00109231  |\n|   0.045 |   0.868 |    141 | arcsinus |   0.08 |         14.38 |         1000 |  0.00146928 | 0.00107488  |\n|   0.049 |   0.843 |    137 | arcsinus |   0.08 |         14.38 |         1000 |  0.00146979 | 0.00128118  |\n|   0.047 |   0.849 |    133 | arcsinus |   0.08 |         14.38 |         1000 |  0.00153956 | 0.00132509  |\n|   0.043 |   0.83  |    131 | arcsinus |   0.08 |         14.38 |         1000 |  0.00165601 | 0.0011438   |\n|   0.044 |   0.833 |    130 | arcsinus |   0.08 |         14.38 |         1000 |  0.00157882 | 0.00122036  |\n|   0.043 |   0.828 |    127 | arcsinus |   0.08 |         14.38 |         1000 |  0.00162113 | 0.00120126  |\n|   0.049 |   0.807 |    123 | arcsinus |   0.08 |         14.38 |         1000 |  0.00173804 | 0.00126107  |\n|   0.049 |   0.807 |    122 | arcsinus |   0.08 |         14.38 |         1000 |  0.00180098 | 0.00129931  |\n|   0.046 |   0.845 |    120 | arcsinus |   0.08 |         14.38 |         1000 |  0.00171958 | 0.00133764  |\n|   0.047 |   0.821 |    119 | arcsinus |   0.08 |         14.38 |         1000 |  0.00176581 | 0.00140853  |\n|   0.049 |   0.804 |    110 | arcsinus |   0.08 |         14.38 |         1000 |  0.00196802 | 0.00140256  |\n+---------+---------+--------+----------+--------+---------------+--------------+-------------+-------------+\n\nThis table represent all optimal sample size which respect statistical condition (type I and II error controlled under H0 and H1 hypothesis).\n\n# IDE Execution (e.g., VS Code, PyCharm)\n\nOpen the script `run_simulation_MAIN.py` and adapt next parameters:\n\n```{python}\n#| echo: True   \n#| output: false \n#| warning: false \n#| error: false   \nfrom script.simulations import *\nfrom script.generate_graph_simulations import *\n\nalpha = 0.05\npower = 0.8\nepsilon_H0 = 0.7\nepsilon_H1 = 0.8\nH0 = 0.7\ncohort_size_start = 200\ncohort_size_end = 10\nnum_simu = 1000\nmethod_stat = \"arcsinus\"\n\ndata = api(cohort_size_start, cohort_size_end, num_simu, epsilon_H0, epsilon_H1, H0, alpha, power, method_stat)\n\n\n```\n\nThen execute the code. In `data` variable you obtain the same resulst that in **Python 3 Terminal Mode** part. If you want obtain graphics which analysis $\\alpha$, $\\beta$ and MSE evolution in function of the sample size you can execute also this function in the same program.\n\n```{python}\n#| echo: True   \n#| output: True \n#| warning: false \n#| error: false   \n\nf1, f2, f3 = graph_api(cohort_size_start, cohort_size_end, num_simu, epsilon_H0, epsilon_H1, H0, alpha, power, method_stat, output_path=\"no save\")\n\nf1.show()\n\nf2.show()\n\nf3.show()\n\n```\n\n# Best sample size obtain\n\nAccording to the situation describe in the benchmark part we can obtain next results in this table.\n\n```{python}\n#| echo: False   \n#| output: False \n#| warning: false \n#| error: false \n\nhtml_table = data.to_html(classes=\"display\", table_id=\"myTable\", index=False)\n\n```\n\n<table border=\"1\" class=\"dataframe display\" id=\"myTable\">\n  <thead>\n    <tr style=\"text-align: right;\">\n      <th>alpha</th>\n      <th>power</th>\n      <th>size</th>\n      <th>method</th>\n      <th>time</th>\n      <th>global_time</th>\n      <th>simulation</th>\n      <th>mse_alpha</th>\n      <th>mse_power</th>\n    </tr>\n  </thead>\n  <tbody>\n    <tr>\n      <td>0.050</td>\n      <td>0.961</td>\n      <td>199</td>\n      <td>arcsinus</td>\n      <td>0.08</td>\n      <td>14.25</td>\n      <td>1000</td>\n      <td>0.001017</td>\n      <td>0.000804</td>\n    </tr>\n    <tr>\n      <td>0.048</td>\n      <td>0.944</td>\n      <td>197</td>\n      <td>arcsinus</td>\n      <td>0.08</td>\n      <td>14.25</td>\n      <td>1000</td>\n      <td>0.001014</td>\n      <td>0.000800</td>\n    </tr>\n    <tr>\n      <td>0.048</td>\n      <td>0.929</td>\n      <td>194</td>\n      <td>arcsinus</td>\n      <td>0.08</td>\n      <td>14.25</td>\n      <td>1000</td>\n      <td>0.001165</td>\n      <td>0.000868</td>\n    </tr>\n    <tr>\n      <td>0.045</td>\n      <td>0.946</td>\n      <td>193</td>\n      <td>arcsinus</td>\n      <td>0.08</td>\n      <td>14.25</td>\n      <td>1000</td>\n      <td>0.000974</td>\n      <td>0.000839</td>\n    </tr>\n    <tr>\n      <td>0.041</td>\n      <td>0.949</td>\n      <td>190</td>\n      <td>arcsinus</td>\n      <td>0.08</td>\n      <td>14.25</td>\n      <td>1000</td>\n      <td>0.001083</td>\n      <td>0.000828</td>\n    </tr>\n    <tr>\n      <td>0.036</td>\n      <td>0.919</td>\n      <td>186</td>\n      <td>arcsinus</td>\n      <td>0.08</td>\n      <td>14.25</td>\n      <td>1000</td>\n      <td>0.001031</td>\n      <td>0.000921</td>\n    </tr>\n    <tr>\n      <td>0.033</td>\n      <td>0.916</td>\n      <td>183</td>\n      <td>arcsinus</td>\n      <td>0.08</td>\n      <td>14.25</td>\n      <td>1000</td>\n      <td>0.001095</td>\n      <td>0.000891</td>\n    </tr>\n    <tr>\n      <td>0.046</td>\n      <td>0.927</td>\n      <td>182</td>\n      <td>arcsinus</td>\n      <td>0.08</td>\n      <td>14.25</td>\n      <td>1000</td>\n      <td>0.001157</td>\n      <td>0.000892</td>\n    </tr>\n    <tr>\n      <td>0.041</td>\n      <td>0.936</td>\n      <td>179</td>\n      <td>arcsinus</td>\n      <td>0.08</td>\n      <td>14.25</td>\n      <td>1000</td>\n      <td>0.001045</td>\n      <td>0.000881</td>\n    </tr>\n    <tr>\n      <td>0.048</td>\n      <td>0.929</td>\n      <td>178</td>\n      <td>arcsinus</td>\n      <td>0.08</td>\n      <td>14.25</td>\n      <td>1000</td>\n      <td>0.001129</td>\n      <td>0.000878</td>\n    </tr>\n    <tr>\n      <td>0.034</td>\n      <td>0.922</td>\n      <td>175</td>\n      <td>arcsinus</td>\n      <td>0.08</td>\n      <td>14.25</td>\n      <td>1000</td>\n      <td>0.001168</td>\n      <td>0.000913</td>\n    </tr>\n    <tr>\n      <td>0.050</td>\n      <td>0.922</td>\n      <td>174</td>\n      <td>arcsinus</td>\n      <td>0.08</td>\n      <td>14.25</td>\n      <td>1000</td>\n      <td>0.001139</td>\n      <td>0.000941</td>\n    </tr>\n    <tr>\n      <td>0.049</td>\n      <td>0.936</td>\n      <td>173</td>\n      <td>arcsinus</td>\n      <td>0.08</td>\n      <td>14.25</td>\n      <td>1000</td>\n      <td>0.001118</td>\n      <td>0.000951</td>\n    </tr>\n    <tr>\n      <td>0.048</td>\n      <td>0.920</td>\n      <td>171</td>\n      <td>arcsinus</td>\n      <td>0.08</td>\n      <td>14.25</td>\n      <td>1000</td>\n      <td>0.001302</td>\n      <td>0.000920</td>\n    </tr>\n    <tr>\n      <td>0.044</td>\n      <td>0.909</td>\n      <td>168</td>\n      <td>arcsinus</td>\n      <td>0.08</td>\n      <td>14.25</td>\n      <td>1000</td>\n      <td>0.001233</td>\n      <td>0.000917</td>\n    </tr>\n    <tr>\n      <td>0.045</td>\n      <td>0.909</td>\n      <td>167</td>\n      <td>arcsinus</td>\n      <td>0.08</td>\n      <td>14.25</td>\n      <td>1000</td>\n      <td>0.001256</td>\n      <td>0.000978</td>\n    </tr>\n    <tr>\n      <td>0.048</td>\n      <td>0.906</td>\n      <td>164</td>\n      <td>arcsinus</td>\n      <td>0.08</td>\n      <td>14.25</td>\n      <td>1000</td>\n      <td>0.001231</td>\n      <td>0.000969</td>\n    </tr>\n    <tr>\n      <td>0.043</td>\n      <td>0.921</td>\n      <td>163</td>\n      <td>arcsinus</td>\n      <td>0.08</td>\n      <td>14.25</td>\n      <td>1000</td>\n      <td>0.001267</td>\n      <td>0.000989</td>\n    </tr>\n    <tr>\n      <td>0.048</td>\n      <td>0.933</td>\n      <td>162</td>\n      <td>arcsinus</td>\n      <td>0.08</td>\n      <td>14.25</td>\n      <td>1000</td>\n      <td>0.001283</td>\n      <td>0.000939</td>\n    </tr>\n    <tr>\n      <td>0.050</td>\n      <td>0.889</td>\n      <td>160</td>\n      <td>arcsinus</td>\n      <td>0.08</td>\n      <td>14.25</td>\n      <td>1000</td>\n      <td>0.001340</td>\n      <td>0.001034</td>\n    </tr>\n    <tr>\n      <td>0.045</td>\n      <td>0.875</td>\n      <td>157</td>\n      <td>arcsinus</td>\n      <td>0.08</td>\n      <td>14.25</td>\n      <td>1000</td>\n      <td>0.001373</td>\n      <td>0.001054</td>\n    </tr>\n    <tr>\n      <td>0.050</td>\n      <td>0.893</td>\n      <td>156</td>\n      <td>arcsinus</td>\n      <td>0.08</td>\n      <td>14.25</td>\n      <td>1000</td>\n      <td>0.001374</td>\n      <td>0.001035</td>\n    </tr>\n    <tr>\n      <td>0.048</td>\n      <td>0.877</td>\n      <td>153</td>\n      <td>arcsinus</td>\n      <td>0.08</td>\n      <td>14.25</td>\n      <td>1000</td>\n      <td>0.001401</td>\n      <td>0.001091</td>\n    </tr>\n    <tr>\n      <td>0.040</td>\n      <td>0.878</td>\n      <td>149</td>\n      <td>arcsinus</td>\n      <td>0.08</td>\n      <td>14.25</td>\n      <td>1000</td>\n      <td>0.001323</td>\n      <td>0.001112</td>\n    </tr>\n    <tr>\n      <td>0.040</td>\n      <td>0.880</td>\n      <td>146</td>\n      <td>arcsinus</td>\n      <td>0.08</td>\n      <td>14.25</td>\n      <td>1000</td>\n      <td>0.001448</td>\n      <td>0.001005</td>\n    </tr>\n    <tr>\n      <td>0.042</td>\n      <td>0.853</td>\n      <td>142</td>\n      <td>arcsinus</td>\n      <td>0.08</td>\n      <td>14.25</td>\n      <td>1000</td>\n      <td>0.001478</td>\n      <td>0.001048</td>\n    </tr>\n    <tr>\n      <td>0.049</td>\n      <td>0.857</td>\n      <td>137</td>\n      <td>arcsinus</td>\n      <td>0.08</td>\n      <td>14.25</td>\n      <td>1000</td>\n      <td>0.001519</td>\n      <td>0.001133</td>\n    </tr>\n    <tr>\n      <td>0.048</td>\n      <td>0.842</td>\n      <td>134</td>\n      <td>arcsinus</td>\n      <td>0.08</td>\n      <td>14.25</td>\n      <td>1000</td>\n      <td>0.001717</td>\n      <td>0.001110</td>\n    </tr>\n    <tr>\n      <td>0.039</td>\n      <td>0.817</td>\n      <td>131</td>\n      <td>arcsinus</td>\n      <td>0.08</td>\n      <td>14.25</td>\n      <td>1000</td>\n      <td>0.001501</td>\n      <td>0.001266</td>\n    </tr>\n    <tr>\n      <td>0.045</td>\n      <td>0.848</td>\n      <td>130</td>\n      <td>arcsinus</td>\n      <td>0.08</td>\n      <td>14.25</td>\n      <td>1000</td>\n      <td>0.001574</td>\n      <td>0.001236</td>\n    </tr>\n    <tr>\n      <td>0.047</td>\n      <td>0.858</td>\n      <td>129</td>\n      <td>arcsinus</td>\n      <td>0.08</td>\n      <td>14.25</td>\n      <td>1000</td>\n      <td>0.001639</td>\n      <td>0.001267</td>\n    </tr>\n    <tr>\n      <td>0.039</td>\n      <td>0.822</td>\n      <td>127</td>\n      <td>arcsinus</td>\n      <td>0.08</td>\n      <td>14.25</td>\n      <td>1000</td>\n      <td>0.001574</td>\n      <td>0.001212</td>\n    </tr>\n    <tr>\n      <td>0.044</td>\n      <td>0.845</td>\n      <td>126</td>\n      <td>arcsinus</td>\n      <td>0.08</td>\n      <td>14.25</td>\n      <td>1000</td>\n      <td>0.001501</td>\n      <td>0.001250</td>\n    </tr>\n    <tr>\n      <td>0.047</td>\n      <td>0.835</td>\n      <td>122</td>\n      <td>arcsinus</td>\n      <td>0.07</td>\n      <td>14.25</td>\n      <td>1000</td>\n      <td>0.001744</td>\n      <td>0.001304</td>\n    </tr>\n    <tr>\n      <td>0.048</td>\n      <td>0.827</td>\n      <td>119</td>\n      <td>arcsinus</td>\n      <td>0.08</td>\n      <td>14.25</td>\n      <td>1000</td>\n      <td>0.001745</td>\n      <td>0.001253</td>\n    </tr>\n    <tr>\n      <td>0.045</td>\n      <td>0.805</td>\n      <td>116</td>\n      <td>arcsinus</td>\n      <td>0.08</td>\n      <td>14.25</td>\n      <td>1000</td>\n      <td>0.001761</td>\n      <td>0.001293</td>\n    </tr>\n    <tr>\n      <td>0.037</td>\n      <td>0.815</td>\n      <td>114</td>\n      <td>arcsinus</td>\n      <td>0.08</td>\n      <td>14.25</td>\n      <td>1000</td>\n      <td>0.001766</td>\n      <td>0.001351</td>\n    </tr>\n  </tbody>\n</table>\n\n\n# Conclusion\n\nThe advantage of this execution mode is you integrate simulation for the sample size in your own statistical program.","srcMarkdownNoYaml":"\n\n\nThis part is to present a simple exemple of sample size process by *Monte Carlo* simulation.\n\n# Python 3 Terminal Mode\n\nOpen your terminal and execute the following command line to obtain a simulation sample size result\n\n```\npython3 run_simulation_terminal_job.py -start 200 -end 10 -NumSimu 1000 -epsilonH0 0.7 -epsilonH1 0.8 -H0 0.7 -alpha 0.05 -power 0.8 -method arcsinus\n```\n\nAll simulations results are printed in the terminal and at the end the following table is printed.\n\n+---------+---------+--------+----------+--------+---------------+--------------+-------------+-------------+\n|   alpha |   power |   size | method   |   time |   global_time |   simulation |   mse_alpha |   mse_power |\n|---------+---------+--------+----------+--------+---------------+--------------+-------------+-------------|\n|   0.031 |   0.93  |    197 | arcsinus |   0.08 |         14.38 |         1000 |  0.00102126 | 0.000875848 |\n|   0.043 |   0.944 |    194 | arcsinus |   0.08 |         14.38 |         1000 |  0.00109952 | 0.000800654 |\n|   0.041 |   0.946 |    193 | arcsinus |   0.08 |         14.38 |         1000 |  0.00110124 | 0.000822513 |\n|   0.049 |   0.923 |    190 | arcsinus |   0.08 |         14.38 |         1000 |  0.00110579 | 0.000867812 |\n|   0.05  |   0.936 |    188 | arcsinus |   0.08 |         14.38 |         1000 |  0.00116913 | 0.000843368 |\n|   0.041 |   0.937 |    185 | arcsinus |   0.08 |         14.38 |         1000 |  0.00104164 | 0.000861563 |\n|   0.043 |   0.918 |    179 | arcsinus |   0.08 |         14.38 |         1000 |  0.00110532 | 0.000951974 |\n|   0.045 |   0.927 |    178 | arcsinus |   0.08 |         14.38 |         1000 |  0.00114249 | 0.000893271 |\n|   0.043 |   0.921 |    171 | arcsinus |   0.08 |         14.38 |         1000 |  0.00117478 | 0.000921501 |\n|   0.048 |   0.916 |    170 | arcsinus |   0.08 |         14.38 |         1000 |  0.00113062 | 0.00094519  |\n|   0.045 |   0.915 |    168 | arcsinus |   0.08 |         14.38 |         1000 |  0.00117041 | 0.000929493 |\n|   0.042 |   0.915 |    167 | arcsinus |   0.08 |         14.38 |         1000 |  0.00116929 | 0.000938062 |\n|   0.047 |   0.923 |    166 | arcsinus |   0.08 |         14.38 |         1000 |  0.00121067 | 0.000925817 |\n|   0.05  |   0.94  |    161 | arcsinus |   0.08 |         14.38 |         1000 |  0.00126986 | 0.000935087 |\n|   0.047 |   0.91  |    158 | arcsinus |   0.08 |         14.38 |         1000 |  0.00130337 | 0.000991019 |\n|   0.038 |   0.877 |    153 | arcsinus |   0.08 |         14.38 |         1000 |  0.0014489  | 0.00108544  |\n|   0.047 |   0.917 |    151 | arcsinus |   0.08 |         14.38 |         1000 |  0.00129249 | 0.00104089  |\n|   0.039 |   0.881 |    149 | arcsinus |   0.08 |         14.38 |         1000 |  0.00148851 | 0.00115507  |\n|   0.05  |   0.89  |    148 | arcsinus |   0.08 |         14.38 |         1000 |  0.00140944 | 0.00104022  |\n|   0.042 |   0.849 |    146 | arcsinus |   0.08 |         14.38 |         1000 |  0.00147038 | 0.00119897  |\n|   0.046 |   0.887 |    145 | arcsinus |   0.08 |         14.38 |         1000 |  0.001362   | 0.00104656  |\n|   0.027 |   0.862 |    142 | arcsinus |   0.08 |         14.38 |         1000 |  0.00147959 | 0.00109231  |\n|   0.045 |   0.868 |    141 | arcsinus |   0.08 |         14.38 |         1000 |  0.00146928 | 0.00107488  |\n|   0.049 |   0.843 |    137 | arcsinus |   0.08 |         14.38 |         1000 |  0.00146979 | 0.00128118  |\n|   0.047 |   0.849 |    133 | arcsinus |   0.08 |         14.38 |         1000 |  0.00153956 | 0.00132509  |\n|   0.043 |   0.83  |    131 | arcsinus |   0.08 |         14.38 |         1000 |  0.00165601 | 0.0011438   |\n|   0.044 |   0.833 |    130 | arcsinus |   0.08 |         14.38 |         1000 |  0.00157882 | 0.00122036  |\n|   0.043 |   0.828 |    127 | arcsinus |   0.08 |         14.38 |         1000 |  0.00162113 | 0.00120126  |\n|   0.049 |   0.807 |    123 | arcsinus |   0.08 |         14.38 |         1000 |  0.00173804 | 0.00126107  |\n|   0.049 |   0.807 |    122 | arcsinus |   0.08 |         14.38 |         1000 |  0.00180098 | 0.00129931  |\n|   0.046 |   0.845 |    120 | arcsinus |   0.08 |         14.38 |         1000 |  0.00171958 | 0.00133764  |\n|   0.047 |   0.821 |    119 | arcsinus |   0.08 |         14.38 |         1000 |  0.00176581 | 0.00140853  |\n|   0.049 |   0.804 |    110 | arcsinus |   0.08 |         14.38 |         1000 |  0.00196802 | 0.00140256  |\n+---------+---------+--------+----------+--------+---------------+--------------+-------------+-------------+\n\nThis table represent all optimal sample size which respect statistical condition (type I and II error controlled under H0 and H1 hypothesis).\n\n# IDE Execution (e.g., VS Code, PyCharm)\n\nOpen the script `run_simulation_MAIN.py` and adapt next parameters:\n\n```{python}\n#| echo: True   \n#| output: false \n#| warning: false \n#| error: false   \nfrom script.simulations import *\nfrom script.generate_graph_simulations import *\n\nalpha = 0.05\npower = 0.8\nepsilon_H0 = 0.7\nepsilon_H1 = 0.8\nH0 = 0.7\ncohort_size_start = 200\ncohort_size_end = 10\nnum_simu = 1000\nmethod_stat = \"arcsinus\"\n\ndata = api(cohort_size_start, cohort_size_end, num_simu, epsilon_H0, epsilon_H1, H0, alpha, power, method_stat)\n\n\n```\n\nThen execute the code. In `data` variable you obtain the same resulst that in **Python 3 Terminal Mode** part. If you want obtain graphics which analysis $\\alpha$, $\\beta$ and MSE evolution in function of the sample size you can execute also this function in the same program.\n\n```{python}\n#| echo: True   \n#| output: True \n#| warning: false \n#| error: false   \n\nf1, f2, f3 = graph_api(cohort_size_start, cohort_size_end, num_simu, epsilon_H0, epsilon_H1, H0, alpha, power, method_stat, output_path=\"no save\")\n\nf1.show()\n\nf2.show()\n\nf3.show()\n\n```\n\n# Best sample size obtain\n\nAccording to the situation describe in the benchmark part we can obtain next results in this table.\n\n```{python}\n#| echo: False   \n#| output: False \n#| warning: false \n#| error: false \n\nhtml_table = data.to_html(classes=\"display\", table_id=\"myTable\", index=False)\n\n```\n\n<table border=\"1\" class=\"dataframe display\" id=\"myTable\">\n  <thead>\n    <tr style=\"text-align: right;\">\n      <th>alpha</th>\n      <th>power</th>\n      <th>size</th>\n      <th>method</th>\n      <th>time</th>\n      <th>global_time</th>\n      <th>simulation</th>\n      <th>mse_alpha</th>\n      <th>mse_power</th>\n    </tr>\n  </thead>\n  <tbody>\n    <tr>\n      <td>0.050</td>\n      <td>0.961</td>\n      <td>199</td>\n      <td>arcsinus</td>\n      <td>0.08</td>\n      <td>14.25</td>\n      <td>1000</td>\n      <td>0.001017</td>\n      <td>0.000804</td>\n    </tr>\n    <tr>\n      <td>0.048</td>\n      <td>0.944</td>\n      <td>197</td>\n      <td>arcsinus</td>\n      <td>0.08</td>\n      <td>14.25</td>\n      <td>1000</td>\n      <td>0.001014</td>\n      <td>0.000800</td>\n    </tr>\n    <tr>\n      <td>0.048</td>\n      <td>0.929</td>\n      <td>194</td>\n      <td>arcsinus</td>\n      <td>0.08</td>\n      <td>14.25</td>\n      <td>1000</td>\n      <td>0.001165</td>\n      <td>0.000868</td>\n    </tr>\n    <tr>\n      <td>0.045</td>\n      <td>0.946</td>\n      <td>193</td>\n      <td>arcsinus</td>\n      <td>0.08</td>\n      <td>14.25</td>\n      <td>1000</td>\n      <td>0.000974</td>\n      <td>0.000839</td>\n    </tr>\n    <tr>\n      <td>0.041</td>\n      <td>0.949</td>\n      <td>190</td>\n      <td>arcsinus</td>\n      <td>0.08</td>\n      <td>14.25</td>\n      <td>1000</td>\n      <td>0.001083</td>\n      <td>0.000828</td>\n    </tr>\n    <tr>\n      <td>0.036</td>\n      <td>0.919</td>\n      <td>186</td>\n      <td>arcsinus</td>\n      <td>0.08</td>\n      <td>14.25</td>\n      <td>1000</td>\n      <td>0.001031</td>\n      <td>0.000921</td>\n    </tr>\n    <tr>\n      <td>0.033</td>\n      <td>0.916</td>\n      <td>183</td>\n      <td>arcsinus</td>\n      <td>0.08</td>\n      <td>14.25</td>\n      <td>1000</td>\n      <td>0.001095</td>\n      <td>0.000891</td>\n    </tr>\n    <tr>\n      <td>0.046</td>\n      <td>0.927</td>\n      <td>182</td>\n      <td>arcsinus</td>\n      <td>0.08</td>\n      <td>14.25</td>\n      <td>1000</td>\n      <td>0.001157</td>\n      <td>0.000892</td>\n    </tr>\n    <tr>\n      <td>0.041</td>\n      <td>0.936</td>\n      <td>179</td>\n      <td>arcsinus</td>\n      <td>0.08</td>\n      <td>14.25</td>\n      <td>1000</td>\n      <td>0.001045</td>\n      <td>0.000881</td>\n    </tr>\n    <tr>\n      <td>0.048</td>\n      <td>0.929</td>\n      <td>178</td>\n      <td>arcsinus</td>\n      <td>0.08</td>\n      <td>14.25</td>\n      <td>1000</td>\n      <td>0.001129</td>\n      <td>0.000878</td>\n    </tr>\n    <tr>\n      <td>0.034</td>\n      <td>0.922</td>\n      <td>175</td>\n      <td>arcsinus</td>\n      <td>0.08</td>\n      <td>14.25</td>\n      <td>1000</td>\n      <td>0.001168</td>\n      <td>0.000913</td>\n    </tr>\n    <tr>\n      <td>0.050</td>\n      <td>0.922</td>\n      <td>174</td>\n      <td>arcsinus</td>\n      <td>0.08</td>\n      <td>14.25</td>\n      <td>1000</td>\n      <td>0.001139</td>\n      <td>0.000941</td>\n    </tr>\n    <tr>\n      <td>0.049</td>\n      <td>0.936</td>\n      <td>173</td>\n      <td>arcsinus</td>\n      <td>0.08</td>\n      <td>14.25</td>\n      <td>1000</td>\n      <td>0.001118</td>\n      <td>0.000951</td>\n    </tr>\n    <tr>\n      <td>0.048</td>\n      <td>0.920</td>\n      <td>171</td>\n      <td>arcsinus</td>\n      <td>0.08</td>\n      <td>14.25</td>\n      <td>1000</td>\n      <td>0.001302</td>\n      <td>0.000920</td>\n    </tr>\n    <tr>\n      <td>0.044</td>\n      <td>0.909</td>\n      <td>168</td>\n      <td>arcsinus</td>\n      <td>0.08</td>\n      <td>14.25</td>\n      <td>1000</td>\n      <td>0.001233</td>\n      <td>0.000917</td>\n    </tr>\n    <tr>\n      <td>0.045</td>\n      <td>0.909</td>\n      <td>167</td>\n      <td>arcsinus</td>\n      <td>0.08</td>\n      <td>14.25</td>\n      <td>1000</td>\n      <td>0.001256</td>\n      <td>0.000978</td>\n    </tr>\n    <tr>\n      <td>0.048</td>\n      <td>0.906</td>\n      <td>164</td>\n      <td>arcsinus</td>\n      <td>0.08</td>\n      <td>14.25</td>\n      <td>1000</td>\n      <td>0.001231</td>\n      <td>0.000969</td>\n    </tr>\n    <tr>\n      <td>0.043</td>\n      <td>0.921</td>\n      <td>163</td>\n      <td>arcsinus</td>\n      <td>0.08</td>\n      <td>14.25</td>\n      <td>1000</td>\n      <td>0.001267</td>\n      <td>0.000989</td>\n    </tr>\n    <tr>\n      <td>0.048</td>\n      <td>0.933</td>\n      <td>162</td>\n      <td>arcsinus</td>\n      <td>0.08</td>\n      <td>14.25</td>\n      <td>1000</td>\n      <td>0.001283</td>\n      <td>0.000939</td>\n    </tr>\n    <tr>\n      <td>0.050</td>\n      <td>0.889</td>\n      <td>160</td>\n      <td>arcsinus</td>\n      <td>0.08</td>\n      <td>14.25</td>\n      <td>1000</td>\n      <td>0.001340</td>\n      <td>0.001034</td>\n    </tr>\n    <tr>\n      <td>0.045</td>\n      <td>0.875</td>\n      <td>157</td>\n      <td>arcsinus</td>\n      <td>0.08</td>\n      <td>14.25</td>\n      <td>1000</td>\n      <td>0.001373</td>\n      <td>0.001054</td>\n    </tr>\n    <tr>\n      <td>0.050</td>\n      <td>0.893</td>\n      <td>156</td>\n      <td>arcsinus</td>\n      <td>0.08</td>\n      <td>14.25</td>\n      <td>1000</td>\n      <td>0.001374</td>\n      <td>0.001035</td>\n    </tr>\n    <tr>\n      <td>0.048</td>\n      <td>0.877</td>\n      <td>153</td>\n      <td>arcsinus</td>\n      <td>0.08</td>\n      <td>14.25</td>\n      <td>1000</td>\n      <td>0.001401</td>\n      <td>0.001091</td>\n    </tr>\n    <tr>\n      <td>0.040</td>\n      <td>0.878</td>\n      <td>149</td>\n      <td>arcsinus</td>\n      <td>0.08</td>\n      <td>14.25</td>\n      <td>1000</td>\n      <td>0.001323</td>\n      <td>0.001112</td>\n    </tr>\n    <tr>\n      <td>0.040</td>\n      <td>0.880</td>\n      <td>146</td>\n      <td>arcsinus</td>\n      <td>0.08</td>\n      <td>14.25</td>\n      <td>1000</td>\n      <td>0.001448</td>\n      <td>0.001005</td>\n    </tr>\n    <tr>\n      <td>0.042</td>\n      <td>0.853</td>\n      <td>142</td>\n      <td>arcsinus</td>\n      <td>0.08</td>\n      <td>14.25</td>\n      <td>1000</td>\n      <td>0.001478</td>\n      <td>0.001048</td>\n    </tr>\n    <tr>\n      <td>0.049</td>\n      <td>0.857</td>\n      <td>137</td>\n      <td>arcsinus</td>\n      <td>0.08</td>\n      <td>14.25</td>\n      <td>1000</td>\n      <td>0.001519</td>\n      <td>0.001133</td>\n    </tr>\n    <tr>\n      <td>0.048</td>\n      <td>0.842</td>\n      <td>134</td>\n      <td>arcsinus</td>\n      <td>0.08</td>\n      <td>14.25</td>\n      <td>1000</td>\n      <td>0.001717</td>\n      <td>0.001110</td>\n    </tr>\n    <tr>\n      <td>0.039</td>\n      <td>0.817</td>\n      <td>131</td>\n      <td>arcsinus</td>\n      <td>0.08</td>\n      <td>14.25</td>\n      <td>1000</td>\n      <td>0.001501</td>\n      <td>0.001266</td>\n    </tr>\n    <tr>\n      <td>0.045</td>\n      <td>0.848</td>\n      <td>130</td>\n      <td>arcsinus</td>\n      <td>0.08</td>\n      <td>14.25</td>\n      <td>1000</td>\n      <td>0.001574</td>\n      <td>0.001236</td>\n    </tr>\n    <tr>\n      <td>0.047</td>\n      <td>0.858</td>\n      <td>129</td>\n      <td>arcsinus</td>\n      <td>0.08</td>\n      <td>14.25</td>\n      <td>1000</td>\n      <td>0.001639</td>\n      <td>0.001267</td>\n    </tr>\n    <tr>\n      <td>0.039</td>\n      <td>0.822</td>\n      <td>127</td>\n      <td>arcsinus</td>\n      <td>0.08</td>\n      <td>14.25</td>\n      <td>1000</td>\n      <td>0.001574</td>\n      <td>0.001212</td>\n    </tr>\n    <tr>\n      <td>0.044</td>\n      <td>0.845</td>\n      <td>126</td>\n      <td>arcsinus</td>\n      <td>0.08</td>\n      <td>14.25</td>\n      <td>1000</td>\n      <td>0.001501</td>\n      <td>0.001250</td>\n    </tr>\n    <tr>\n      <td>0.047</td>\n      <td>0.835</td>\n      <td>122</td>\n      <td>arcsinus</td>\n      <td>0.07</td>\n      <td>14.25</td>\n      <td>1000</td>\n      <td>0.001744</td>\n      <td>0.001304</td>\n    </tr>\n    <tr>\n      <td>0.048</td>\n      <td>0.827</td>\n      <td>119</td>\n      <td>arcsinus</td>\n      <td>0.08</td>\n      <td>14.25</td>\n      <td>1000</td>\n      <td>0.001745</td>\n      <td>0.001253</td>\n    </tr>\n    <tr>\n      <td>0.045</td>\n      <td>0.805</td>\n      <td>116</td>\n      <td>arcsinus</td>\n      <td>0.08</td>\n      <td>14.25</td>\n      <td>1000</td>\n      <td>0.001761</td>\n      <td>0.001293</td>\n    </tr>\n    <tr>\n      <td>0.037</td>\n      <td>0.815</td>\n      <td>114</td>\n      <td>arcsinus</td>\n      <td>0.08</td>\n      <td>14.25</td>\n      <td>1000</td>\n      <td>0.001766</td>\n      <td>0.001351</td>\n    </tr>\n  </tbody>\n</table>\n\n\n# Conclusion\n\nThe advantage of this execution mode is you integrate simulation for the sample size in your own statistical program."},"formats":{"html":{"identifier":{"display-name":"HTML","target-format":"html","base-format":"html"},"execute":{"fig-width":7,"fig-height":5,"fig-format":"retina","fig-dpi":96,"df-print":"default","error":false,"eval":true,"cache":null,"freeze":false,"echo":true,"output":true,"warning":true,"include":true,"keep-md":false,"keep-ipynb":false,"ipynb":null,"enabled":null,"daemon":null,"daemon-restart":false,"debug":false,"ipynb-filters":[],"ipynb-shell-interactivity":null,"plotly-connected":true,"engine":"jupyter"},"render":{"keep-tex":false,"keep-typ":false,"keep-source":false,"keep-hidden":false,"prefer-html":false,"output-divs":true,"output-ext":"html","fig-align":"default","fig-pos":null,"fig-env":null,"code-fold":true,"code-overflow":"scroll","code-link":false,"code-line-numbers":false,"code-tools":false,"tbl-colwidths":"auto","merge-includes":true,"inline-includes":false,"preserve-yaml":false,"latex-auto-mk":true,"latex-auto-install":true,"latex-clean":true,"latex-min-runs":1,"latex-max-runs":10,"latex-makeindex":"makeindex","latex-makeindex-opts":[],"latex-tlmgr-opts":[],"latex-input-paths":[],"latex-output-dir":null,"link-external-icon":false,"link-external-newwindow":false,"self-contained-math":false,"format-resources":[],"notebook-links":true},"pandoc":{"standalone":true,"wrap":"none","default-image-extension":"png","to":"html","toc":true,"output-file":"exemple_python.html"},"language":{"toc-title-document":"Table of contents","toc-title-website":"On this page","related-formats-title":"Other Formats","related-notebooks-title":"Notebooks","source-notebooks-prefix":"Source","other-links-title":"Other Links","code-links-title":"Code Links","launch-dev-container-title":"Launch Dev Container","launch-binder-title":"Launch Binder","article-notebook-label":"Article Notebook","notebook-preview-download":"Download Notebook","notebook-preview-download-src":"Download Source","notebook-preview-back":"Back to Article","manuscript-meca-bundle":"MECA Bundle","section-title-abstract":"Abstract","section-title-appendices":"Appendices","section-title-footnotes":"Footnotes","section-title-references":"References","section-title-reuse":"Reuse","section-title-copyright":"Copyright","section-title-citation":"Citation","appendix-attribution-cite-as":"For attribution, please cite this work as:","appendix-attribution-bibtex":"BibTeX citation:","appendix-view-license":"View License","title-block-author-single":"Author","title-block-author-plural":"Authors","title-block-affiliation-single":"Affiliation","title-block-affiliation-plural":"Affiliations","title-block-published":"Published","title-block-modified":"Modified","title-block-keywords":"Keywords","callout-tip-title":"Tip","callout-note-title":"Note","callout-warning-title":"Warning","callout-important-title":"Important","callout-caution-title":"Caution","code-summary":"Code","code-tools-menu-caption":"Code","code-tools-show-all-code":"Show All Code","code-tools-hide-all-code":"Hide All Code","code-tools-view-source":"View Source","code-tools-source-code":"Source Code","tools-share":"Share","tools-download":"Download","code-line":"Line","code-lines":"Lines","copy-button-tooltip":"Copy to Clipboard","copy-button-tooltip-success":"Copied!","repo-action-links-edit":"Edit this page","repo-action-links-source":"View source","repo-action-links-issue":"Report an issue","back-to-top":"Back to top","search-no-results-text":"No results","search-matching-documents-text":"matching documents","search-copy-link-title":"Copy link to search","search-hide-matches-text":"Hide additional matches","search-more-match-text":"more match in this document","search-more-matches-text":"more matches in this document","search-clear-button-title":"Clear","search-text-placeholder":"","search-detached-cancel-button-title":"Cancel","search-submit-button-title":"Submit","search-label":"Search","toggle-section":"Toggle section","toggle-sidebar":"Toggle sidebar navigation","toggle-dark-mode":"Toggle dark mode","toggle-reader-mode":"Toggle reader mode","toggle-navigation":"Toggle navigation","crossref-fig-title":"Figure","crossref-tbl-title":"Table","crossref-lst-title":"Listing","crossref-thm-title":"Theorem","crossref-lem-title":"Lemma","crossref-cor-title":"Corollary","crossref-prp-title":"Proposition","crossref-cnj-title":"Conjecture","crossref-def-title":"Definition","crossref-exm-title":"Example","crossref-exr-title":"Exercise","crossref-ch-prefix":"Chapter","crossref-apx-prefix":"Appendix","crossref-sec-prefix":"Section","crossref-eq-prefix":"Equation","crossref-lof-title":"List of Figures","crossref-lot-title":"List of Tables","crossref-lol-title":"List of Listings","environment-proof-title":"Proof","environment-remark-title":"Remark","environment-solution-title":"Solution","listing-page-order-by":"Order By","listing-page-order-by-default":"Default","listing-page-order-by-date-asc":"Oldest","listing-page-order-by-date-desc":"Newest","listing-page-order-by-number-desc":"High to Low","listing-page-order-by-number-asc":"Low to High","listing-page-field-date":"Date","listing-page-field-title":"Title","listing-page-field-description":"Description","listing-page-field-author":"Author","listing-page-field-filename":"File Name","listing-page-field-filemodified":"Modified","listing-page-field-subtitle":"Subtitle","listing-page-field-readingtime":"Reading Time","listing-page-field-wordcount":"Word Count","listing-page-field-categories":"Categories","listing-page-minutes-compact":"{0} min","listing-page-category-all":"All","listing-page-no-matches":"No matching items","listing-page-words":"{0} words","listing-page-filter":"Filter","draft":"Draft"},"metadata":{"lang":"en","fig-responsive":true,"quarto-version":"1.5.57","theme":{"light":"cosmo","dark":"darkly"},"toc-title":"Contents","toc-location":"left","title":"","jupyter":"python3"},"extensions":{"book":{"multiFile":true}}}},"projectFormats":["html"]}